Metadata-Version: 2.4
Name: image-processing-rluispdev
Version: 0.1
Summary: Image Processing Package Using Skimage
Home-page: https://github.com/rluispdev/image-processing-package
Author: rluispdev
Requires-Python: >=3.6
Requires-Dist: matplotlib
Requires-Dist: numpy
Requires-Dist: scikit-image>=0.16.1
Dynamic: author
Dynamic: description
Dynamic: description-content-type
Dynamic: home-page
Dynamic: requires-dist
Dynamic: requires-python
Dynamic: summary
